uptick_datawarehouse/__init__.py
uptick_datawarehouse/model_settings.py
uptick_datawarehouse/finance/__init__.py
uptick_datawarehouse/finance/models.py
uptick_datawarehouse/finance/migrations/0001_initial.py
uptick_datawarehouse/finance/migrations/__init__.py
uptick_datawarehouse/hubspot/__init__.py
uptick_datawarehouse/hubspot/apps.py
uptick_datawarehouse/hubspot/models.py
uptick_datawarehouse/hubspot/migrations/0001_schema.py
uptick_datawarehouse/hubspot/migrations/0002_initial.py
uptick_datawarehouse/hubspot/migrations/__init__.py
uptick_datawarehouse/mixpanel/__init__.py
uptick_datawarehouse/mixpanel/apps.py
uptick_datawarehouse/mixpanel/models.py
uptick_datawarehouse/mixpanel/migrations/0001_schema.py
uptick_datawarehouse/mixpanel/migrations/0002_initial.py
uptick_datawarehouse/mixpanel/migrations/0003_alter_mixpanelusercohort_cohort_name.py
uptick_datawarehouse/mixpanel/migrations/__init__.py
uptick_datawarehouse/subscriptionmanager/__init__.py
uptick_datawarehouse/subscriptionmanager/apps.py
uptick_datawarehouse/subscriptionmanager/models.py
uptick_datawarehouse/subscriptionmanager/tests.py
uptick_datawarehouse/subscriptionmanager/migrations/0001_schema.py
uptick_datawarehouse/subscriptionmanager/migrations/0002_changesummary_chargesummary_paymentmethodsummary_recurringcreditsummary_revenueforecastsummary_subsc.py
uptick_datawarehouse/subscriptionmanager/migrations/0003_auto_20230123_0443.py
uptick_datawarehouse/subscriptionmanager/migrations/0004_auto_20231009_1407.py
uptick_datawarehouse/subscriptionmanager/migrations/0005_consolidatedprofitandlossmonth.py
uptick_datawarehouse/subscriptionmanager/migrations/0006_alter_reporting_fx_rate_2024_04_15.py
uptick_datawarehouse/subscriptionmanager/migrations/0007_auto_20240516_0257.py
uptick_datawarehouse/subscriptionmanager/migrations/0008_auto_20240531_1445.py
uptick_datawarehouse/subscriptionmanager/migrations/0009_subscriptionsummary_billing_entity_name.py
uptick_datawarehouse-0.8.0.dist-info/METADATA
uptick_datawarehouse-0.8.0.dist-info/WHEEL
uptick_datawarehouse-0.8.0.dist-info/RECORD
