Metadata-Version: 2.4
Name: uptick-datawarehouse
Version: 0.8.0
Summary: Uptick Data Warehouse Schemas
Requires-Python: >=3.12
Requires-Dist: django<5.2.0,>=3.2
